{
  "_fv": 69,
  "_type": "gui",
  "definition": {
    "type": 0,
    "width": 141,
    "height": 107,
    "inventoryOffsetX": 0,
    "inventoryOffsetY": 0,
    "renderBgLayer": true,
    "doesPauseGame": false,
    "components": [
      {
        "type": "textfield",
        "data": {
          "placeholder": "",
          "name": "receiver",
          "width": 120,
          "height": 20,
          "x": 154,
          "y": 120
        }
      },
      {
        "type": "textfield",
        "data": {
          "placeholder": "",
          "name": "amount",
          "width": 120,
          "height": 20,
          "x": 154,
          "y": 87
        }
      },
      {
        "type": "label",
        "data": {
          "name": "label_amount",
          "text": {
            "fixedValue": "Amount"
          },
          "color": {
            "value": -12829636,
            "falpha": 0.0
          },
          "x": 199,
          "y": 77
        }
      },
      {
        "type": "label",
        "data": {
          "name": "label_receiver",
          "text": {
            "fixedValue": "Receiver"
          },
          "color": {
            "value": -12829636,
            "falpha": 0.0
          },
          "x": 193,
          "y": 110
        }
      },
      {
        "type": "button",
        "data": {
          "name": "button_empty",
          "text": "Transfer",
          "isUndecorated": false,
          "onClick": {
            "name": "TransferMoneyClicked"
          },
          "width": 119,
          "height": 20,
          "x": 154,
          "y": 143
        }
      }
    ],
    "gridSettings": {
      "sx": 14,
      "sy": 14,
      "ox": 13,
      "oy": 15,
      "snapOnGrid": false
    }
  }
}